idr_gallery/__init__.py
idr_gallery/apps.py
idr_gallery/gallery_settings.py
idr_gallery/settings.py
idr_gallery/urls.py
idr_gallery/utils.py
idr_gallery/version.py
idr_gallery/views.py
idr_gallery/__pycache__/__init__.cpython-310.pyc
idr_gallery/__pycache__/version.cpython-310.pyc
idr_gallery/data/background_images.py
idr_gallery/data/tabs.py
idr_gallery/static/idr_gallery/autocomplete.js
idr_gallery/static/idr_gallery/categories.js
idr_gallery/static/idr_gallery/model.js
idr_gallery/static/idr_gallery/omero_search_form.js
idr_gallery/static/idr_gallery/search.js
idr_gallery/static/idr_gallery/studies.css
idr_gallery/static/idr_gallery/version.js
idr_gallery/static/idr_gallery/3rdparty/babel-core/browser-polyfill_5.6.15.min.js
idr_gallery/static/idr_gallery/3rdparty/bootstrap-3.1.1/css/bootstrap-theme.css
idr_gallery/static/idr_gallery/3rdparty/bootstrap-3.1.1/css/bootstrap-theme.css.map
idr_gallery/static/idr_gallery/3rdparty/bootstrap-3.1.1/css/bootstrap-theme.min.css
idr_gallery/static/idr_gallery/3rdparty/bootstrap-3.1.1/css/bootstrap.css
idr_gallery/static/idr_gallery/3rdparty/bootstrap-3.1.1/css/bootstrap.css.map
idr_gallery/static/idr_gallery/3rdparty/bootstrap-3.1.1/css/bootstrap.min.css
idr_gallery/static/idr_gallery/3rdparty/bootstrap-3.1.1/fonts/glyphicons-halflings-regular.eot
idr_gallery/static/idr_gallery/3rdparty/bootstrap-3.1.1/fonts/glyphicons-halflings-regular.svg
idr_gallery/static/idr_gallery/3rdparty/bootstrap-3.1.1/fonts/glyphicons-halflings-regular.ttf
idr_gallery/static/idr_gallery/3rdparty/bootstrap-3.1.1/fonts/glyphicons-halflings-regular.woff
idr_gallery/static/idr_gallery/3rdparty/bootstrap-3.1.1/js/bootstrap.js
idr_gallery/static/idr_gallery/3rdparty/bootstrap-3.1.1/js/bootstrap.min.js
idr_gallery/static/idr_gallery/3rdparty/foundation/foundation.min.css
idr_gallery/static/idr_gallery/3rdparty/foundation/foundation.min.js
idr_gallery/static/idr_gallery/3rdparty/jquery/jquery-2.2.4.min.js
idr_gallery-3.13.1.dist-info/licenses/LICENSE
idr_gallery-3.13.1.dist-info/METADATA
idr_gallery-3.13.1.dist-info/WHEEL
idr_gallery-3.13.1.dist-info/top_level.txt
idr_gallery-3.13.1.dist-info/RECORD
